challenge_4_simple_linear_regression/__init__.py
challenge_4_simple_linear_regression/challenge_4_simple_linear_regression.py
challenge_4_simple_linear_regression/cli.py
challenge_4_simple_linear_regression-0.1.0.dist-info/AUTHORS.rst
challenge_4_simple_linear_regression-0.1.0.dist-info/LICENSE
challenge_4_simple_linear_regression-0.1.0.dist-info/METADATA
challenge_4_simple_linear_regression-0.1.0.dist-info/WHEEL
challenge_4_simple_linear_regression-0.1.0.dist-info/entry_points.txt
challenge_4_simple_linear_regression-0.1.0.dist-info/top_level.txt
challenge_4_simple_linear_regression-0.1.0.dist-info/RECORD
