Metadata-Version: 2.1
Name: challenge-4-simple-linear-regression
Version: 0.1.0
Summary: Challenge 4 Simple Linear Regression Model
Home-page: https://github.com/zedki7/challenge_4_simple_linear_regression
Author: Zakaria BABAOUSMAIL
Author-email: z.babaousmail@esi-sba.dz
License: MIT license
Keywords: challenge_4_simple_linear_regression
Classifier: Development Status :: 2 - Pre-Alpha
Classifier: Intended Audience :: Developers
Classifier: License :: OSI Approved :: MIT License
Classifier: Natural Language :: English
Classifier: Programming Language :: Python :: 3
Classifier: Programming Language :: Python :: 3.6
Classifier: Programming Language :: Python :: 3.7
Classifier: Programming Language :: Python :: 3.8
Requires-Python: >=3.6
License-File: LICENSE
License-File: AUTHORS.rst
Requires-Dist: Click (>=7.0)
